deeplookup/__init__.py
deeplookup/bigram.py
deeplookup/datasets.py
deeplookup/env.py
deeplookup/metrics.py
deeplookup/nn.py
deeplookup/qnn.py
deeplookup/resolver.py
deeplookup/svm.py
deeplookup/ts.py
deeplookup/version.py
deeplookup/vis.py
deeplookup/datasets/__init__.py
deeplookup/datasets/core.py
deeplookup/datasets/gta1.py
deeplookup/datasets/gtabench.py
deeplookup/experiments/__init__.py
deeplookup/experiments/dga.py
deeplookup/experiments/hmm.py
deeplookup/experiments/pomdp.py
deeplookup/experiments/tunneling.py
deeplookup/pipelines/__init__.py
deeplookup/pipelines/gta1.py
deeplookup/pipelines/gta1_trainer.py
deeplookup/weights/__init__.py
deeplookup/weights/b-dga-ybubnov.h5
deeplookup/weights/gta-v0.h5
deeplookup/weights/gta-v1.h5
deeplookup-1.0.0.dist-info/LICENSE
deeplookup-1.0.0.dist-info/METADATA
deeplookup-1.0.0.dist-info/WHEEL
deeplookup-1.0.0.dist-info/top_level.txt
deeplookup-1.0.0.dist-info/RECORD
