Metadata-Version: 2.1
Name: deeplookup
Version: 1.0.0
Summary: Deep Lookup - Deep Learning for Domain Name System
Home-page: https://github.com/ybubnov/deep-lookup
Author: Yasha Bubnov
Author-email: girokompass@gmail.com
License: UNKNOWN
Platform: UNKNOWN
Classifier: Intended Audience :: Developers
Classifier: License :: OSI Approved :: Apache Software License
Requires-Dist: nltk
Requires-Dist: scipy
Requires-Dist: sklearn
Requires-Dist: gym
Requires-Dist: pandas
Requires-Dist: matplotlib
Requires-Dist: numpy
Requires-Dist: keract
Requires-Dist: h5py
Requires-Dist: tensorflow (>=2.0.0)
Requires-Dist: tensorflow-datasets (>=4.0.0)
Requires-Dist: tensorflow-text (>=2.0.0)
Requires-Dist: tensorflow-transform (>=1.0.0)
Requires-Dist: tfx (>=1.0.0)
Requires-Dist: pyts (>=0.11.0)
Requires-Dist: keras-rl2 (>=1.0.4)
Requires-Dist: wandb (>=0.12.0)
Requires-Dist: dnspython (>=2.1.0)
